odoo/addons/purchase_order_revision/README.rst
odoo/addons/purchase_order_revision/__init__.py
odoo/addons/purchase_order_revision/__manifest__.py
odoo/addons/purchase_order_revision/i18n/it.po
odoo/addons/purchase_order_revision/i18n/purchase_order_revision.pot
odoo/addons/purchase_order_revision/i18n/tr.po
odoo/addons/purchase_order_revision/models/__init__.py
odoo/addons/purchase_order_revision/models/purchase_order.py
odoo/addons/purchase_order_revision/readme/CONTRIBUTORS.rst
odoo/addons/purchase_order_revision/readme/DESCRIPTION.rst
odoo/addons/purchase_order_revision/readme/INSTALL.rst
odoo/addons/purchase_order_revision/static/description/icon.png
odoo/addons/purchase_order_revision/static/description/index.html
odoo/addons/purchase_order_revision/tests/__init__.py
odoo/addons/purchase_order_revision/tests/test_purchase_order_revision.py
odoo/addons/purchase_order_revision/view/purchase_order.xml
odoo_addon_purchase_order_revision-16.0.1.0.0.7.dist-info/METADATA
odoo_addon_purchase_order_revision-16.0.1.0.0.7.dist-info/WHEEL
odoo_addon_purchase_order_revision-16.0.1.0.0.7.dist-info/top_level.txt
odoo_addon_purchase_order_revision-16.0.1.0.0.7.dist-info/RECORD
