Metadata-Version: 2.1
Name: odoo-addon-purchase_order_revision
Version: 16.0.1.0.0.7
Summary: Keep track of revised quotations
Home-page: https://github.com/OCA/purchase-workflow
Author: Open Source Integrators,Odoo Community Association (OCA)
Author-email: support@odoo-community.org
License: AGPL-3
Classifier: Programming Language :: Python
Classifier: Framework :: Odoo
Classifier: Framework :: Odoo :: 16.0
Classifier: License :: OSI Approved :: GNU Affero General Public License v3
Requires-Python: >=3.10
Requires-Dist: odoo-addon-base-revision<16.1dev,>=16.0dev
Requires-Dist: odoo<16.1dev,>=16.0a
